openhands/__init__.py
openhands/__version.py
openhands/hub.py
openhands/apis/__init__.py
openhands/apis/classification_model.py
openhands/apis/dpc.py
openhands/apis/inference.py
openhands/core/__init__.py
openhands/core/data.py
openhands/core/exp_utils.py
openhands/core/losses.py
openhands/datasets/__init__.py
openhands/datasets/data_readers.py
openhands/datasets/pose_transforms.py
openhands/datasets/video_transforms.py
openhands/datasets/assets/asllvd_metadata/label_names.txt
openhands/datasets/assets/asllvd_metadata/normalized_glosses.csv
openhands/datasets/assets/asllvd_metadata/test_labels.json
openhands/datasets/assets/asllvd_metadata/train_labels.json
openhands/datasets/assets/autsl_metadata/normalized_glosses.csv
openhands/datasets/assets/autsl_metadata/AUTSL/SignList_ClassId_TR_EN.csv
openhands/datasets/assets/autsl_metadata/AUTSL/test_labels.csv
openhands/datasets/assets/autsl_metadata/AUTSL/train_labels.csv
openhands/datasets/assets/autsl_metadata/AUTSL/validation_labels.csv
openhands/datasets/assets/bosphorus22k_metadata/BosphorusSign22k.csv
openhands/datasets/assets/bosphorus22k_metadata/BosphorusSign22k_classes.csv
openhands/datasets/assets/bosphorus22k_metadata/normalized_glosses.csv
openhands/datasets/assets/csl_metadata/normalized_glosses.csv
openhands/datasets/assets/csl_metadata/split.test.csv
openhands/datasets/assets/csl_metadata/split.train.csv
openhands/datasets/assets/csl_metadata/CSL/gloss_label.txt
openhands/datasets/assets/csl_metadata/CSL/readme.txt
openhands/datasets/assets/devisign_metadata/normalized_glosses.csv
openhands/datasets/assets/devisign_metadata/split.test.csv
openhands/datasets/assets/devisign_metadata/split.train.csv
openhands/datasets/assets/devisign_metadata/Documents/4414To2000(DEVISIGN_L)_ID&Meaning.txt
openhands/datasets/assets/devisign_metadata/Documents/4414To36(DEVISIGN_G)_ID&Meaning.txt
openhands/datasets/assets/devisign_metadata/Documents/4414To500(DEVISIGN_D)_ID&Meaning.txt
openhands_sl-0.1.13.dist-info/LICENSE.txt
openhands_sl-0.1.13.dist-info/METADATA
openhands_sl-0.1.13.dist-info/WHEEL
openhands_sl-0.1.13.dist-info/top_level.txt
openhands_sl-0.1.13.dist-info/RECORD
