Metadata-Version: 2.1
Name: openhands-sl
Version: 0.1.13
Summary: 👐OpenHands : Making Sign Language Recognition Accessible
Home-page: https://openhands.ai4bharat.org
Download-URL: https://pypi.org/project/openhands_sl
Author: AI4Bhārat
Project-URL: Source, https://github.com/AI4Bharat/OpenHands
Project-URL: Issues, https://github.com/AI4Bharat/OpenHands/issues
Project-URL: Documentation, https://openhands.readthedocs.io
Classifier: Programming Language :: Python :: 3
Classifier: Operating System :: OS Independent
Classifier: Topic :: Scientific/Engineering :: Artificial Intelligence
Classifier: Topic :: Software Development :: Libraries
License-File: LICENSE.txt
Requires-Dist: numpy==1.23.5
Requires-Dist: albumentations==1.3.1
Requires-Dist: tqdm==4.64.1
Requires-Dist: PyYAML==6.0
Requires-Dist: omegaconf==2.3.0
Requires-Dist: pytorch-lightning==1.9.5
Requires-Dist: pytorchvideo==0.1.5
Requires-Dist: hydra-core==1.3.2
Requires-Dist: torch==2.0.1
Requires-Dist: mediapipe==0.10.9
Requires-Dist: natsort==8.4.0
Requires-Dist: h5py==3.9.0
Requires-Dist: torchvision==0.15.2
Requires-Dist: opencv-python-headless==4.8.1.78
Requires-Dist: torchmetrics==0.11.4
Requires-Dist: timm==0.9.16
Requires-Dist: transformers==4.35.2
Requires-Dist: pandas==2.0.3
Requires-Dist: Pillow==10.0.1
Requires-Dist: scikit-learn==1.3.2
Requires-Dist: beautifulsoup4==4.12.2
Requires-Dist: lxml==4.9.3
Requires-Dist: sphinx==4.3.2
Requires-Dist: myst-parser==0.16.1
Requires-Dist: sphinx-rtd-theme==1.0.0
Requires-Dist: sphinx-copybutton==0.4.0
